<?xml version="1.0" encoding="UTF-8"?>
<Defs>

	<!--
		vertical <researchViewY>1</researchViewY>
		horizontal <researchViewX>1</researchViewX>
	-->

	<!--******** META ********-->

	<ResearchProjectDef Abstract="True" Name="ConcreteBarricade_Research">
		<baseCost>200</baseCost>
		<techLevel>Industrial</techLevel>
	</ResearchProjectDef>

	<!--******** INHERET ********-->

	<ResearchProjectDef ParentName="ConcreteBarricade_Research">
		<defName>ConcreteBarricade_Basic</defName>
		<prerequisites><li>VMEu_ConcreteMaking</li></prerequisites>
		<label>Concrete Barricade</label>
		<description>Unlock cheap layered concrete barricades for tougher and quicker protection</description>
		<researchViewX>3</researchViewX>
		<researchViewY>5.1</researchViewY>
	</ResearchProjectDef>
</Defs>
